<?xml version="1.0" encoding="UTF-8"?><database>
    <element label="Trivia Game Instance" max_length="40" name="x_275551_trivia_ga_trivia_game_instance" type="collection">
        <element label="Answer" max_length="1000" name="answer" type="string"/>
        <element attributes="edge_encryption_enabled=true,no_sort=true,slushbucket_ref_no_expand=true" label="Choices" max_length="4000" name="choices" reference="x_275551_trivia_ga_trivia_question_choices" reference_qual="trivia_questionSAMEAStrivia_question^EQ" reference_qual_condition="trivia_questionSAMEAStrivia_question^EQ" type="glide_list"/>
        <element attributes="edge_encryption_enabled=true" label="Correct" max_length="40" name="correct" type="boolean"/>
        <element attributes="edge_encryption_enabled=true,encode_utf8=false" label="Player" max_length="32" name="player" reference="sys_user" type="reference"/>
        <element attributes="edge_encryption_enabled=true,encode_utf8=false" label="Trivia Game" max_length="32" name="trivia_game" reference="x_275551_trivia_ga_trivia_game" type="reference"/>
        <element attributes="edge_encryption_enabled=true,encode_utf8=false" label="Trivia question" max_length="32" name="trivia_question" reference="x_275551_trivia_ga_trivia_questions" type="reference"/>
        <index name="index">
            <element name="trivia_question"/>
        </index>
        <index name="index2">
            <element name="trivia_game"/>
        </index>
        <index name="index3">
            <element name="player"/>
        </index>
    </element>
</database>
